codesense/__init__.py
codesense/api.py
codesense/cli.py
codesense/config/__init__.py
codesense/config/settings.py
codesense/parsers/__init__.py
codesense/parsers/base_parser.py
codesense/parsers/python_parsers.py
codesense/tools/__init__.py
codesense/tools/indexer.py
codesense/tools/searcher.py
codesense/util/__init__.py
codesense/util/embeddings.py
codesense/util/storage.py
codesense-0.4.0.dist-info/licenses/LICENSE
codesense-0.4.0.dist-info/METADATA
codesense-0.4.0.dist-info/WHEEL
codesense-0.4.0.dist-info/entry_points.txt
codesense-0.4.0.dist-info/top_level.txt
codesense-0.4.0.dist-info/RECORD
