Metadata-Version: 2.4
Name: codesense
Version: 0.4.0
Summary: AI-powered semantic code search with intelligent parsing for Python projects
Author-email: Artem <stasiuk.dev@gmail.com>
Maintainer-email: Artem <stasiuk.dev@gmail.com>
License: MIT
Project-URL: Homepage, https://github.com/steliarix/codesense
Project-URL: Documentation, https://github.com/steliarix/codesense#readme
Project-URL: Repository, https://github.com/steliarix/codesense
Project-URL: Issues, https://github.com/steliarix/codesense/issues
Project-URL: Changelog, https://github.com/steliarix/codesense/blob/main/CHANGELOG.md
Keywords: codesense,semantic-search,code-search,embeddings,faiss,sentence-transformers,ai,machine-learning,nlp,developer-tools
Classifier: Development Status :: 3 - Alpha
Classifier: Intended Audience :: Developers
Classifier: Topic :: Software Development :: Libraries :: Python Modules
Classifier: Topic :: Software Development :: Code Generators
Classifier: License :: OSI Approved :: MIT License
Classifier: Programming Language :: Python :: 3
Classifier: Programming Language :: Python :: 3.9
Classifier: Programming Language :: Python :: 3.10
Classifier: Programming Language :: Python :: 3.11
Classifier: Programming Language :: Python :: 3.12
Classifier: Programming Language :: Python :: 3.13
Classifier: Operating System :: OS Independent
Requires-Python: >=3.9
License-File: LICENSE
Requires-Dist: sentence-transformers>=2.0.0
Requires-Dist: faiss-cpu>=1.7.0
Requires-Dist: click>=8.0.0
Requires-Dist: tqdm>=4.65.0
Requires-Dist: numpy>=1.21.0
Requires-Dist: torch>=2.0.0
Provides-Extra: dev
Requires-Dist: pytest>=7.0.0; extra == "dev"
Requires-Dist: pytest-cov>=4.0.0; extra == "dev"
Requires-Dist: black>=23.0.0; extra == "dev"
Requires-Dist: ruff>=0.1.0; extra == "dev"
Requires-Dist: mypy>=1.0.0; extra == "dev"
Dynamic: license-file
